Metadata-Version: 2.1
Name: homekit
Version: 0.18.0
Summary: Python code to interface HomeKit Accessories and Controllers
Home-page: https://github.com/jlusiardi/homekit_python
Author: Joachim Lusiardi
Author-email: pypi@lusiardi.de
License: Apache License 2.0
Download-URL: https://github.com/jlusiardi/homekit_python/archive/0.18.0.tar.gz
Keywords: HomeKit
Platform: UNKNOWN
Classifier: License :: OSI Approved :: Apache Software License
Classifier: Topic :: Home Automation
Classifier: Intended Audience :: Developers
Classifier: Intended Audience :: End Users/Desktop
Requires-Dist: cryptography (>=2.5)
Requires-Dist: ed25519
Requires-Dist: hkdf
Requires-Dist: tlv8 (>=0.9.0)
Provides-Extra: ble
Requires-Dist: dbus-python ; extra == 'ble'
Requires-Dist: gatt ; extra == 'ble'
Requires-Dist: pygobject ; extra == 'ble'
Provides-Extra: ip
Requires-Dist: zeroconf ; extra == 'ip'
